dspawpy/__init__.py
dspawpy/plot.py
dspawpy/analysis/__init__.py
dspawpy/analysis/aimdtools.py
dspawpy/analysis/post_relax.py
dspawpy/analysis/vacf.py
dspawpy/cli/__init__.py
dspawpy/cli/auxiliary.py
dspawpy/cli/entrypoint.py
dspawpy/cli/menu10.py
dspawpy/cli/menu13.py
dspawpy/cli/menu15.py
dspawpy/cli/menu3.py
dspawpy/cli/menu4.py
dspawpy/cli/menu5.py
dspawpy/cli/menu6.py
dspawpy/cli/menu8.py
dspawpy/cli/menu9.py
dspawpy/cli/menu_prompts.py
dspawpy/cli/times+simsun.ttf
dspawpy/diffusion/__init__.py
dspawpy/diffusion/neb.py
dspawpy/diffusion/nebtools.py
dspawpy/diffusion/pathfinder.py
dspawpy/io/__init__.py
dspawpy/io/export.py
dspawpy/io/read.py
dspawpy/io/structure.py
dspawpy/io/utils.py
dspawpy/io/write.py
dspawpy-1.8.4.dist-info/METADATA
dspawpy-1.8.4.dist-info/WHEEL
dspawpy-1.8.4.dist-info/entry_points.txt
dspawpy-1.8.4.dist-info/licenses/LICENSE.txt
dspawpy-1.8.4.dist-info/RECORD
