Metadata-Version: 2.4
Name: dspawpy
Version: 1.8.4
Summary: Tools for dspaw
Project-URL: homepage, http://cloud.hzwtech.com/
Author: txwang, ymxia, syyl, hql
Author-email: zzl <ZhengZhilin@hzwtech.com>
Maintainer-email: zzl <ZhengZhilin@hzwtech.com>
License: Copyright (c) 2023 HZWTECH.COM
License-File: LICENSE.txt
Keywords: atom,band-structure,density-of-states,dft,ds-paw,hzw,pymatgen,quantum chemistry,structure
Classifier: Programming Language :: Python :: 3 :: Only
Classifier: Programming Language :: Python :: 3.9
Classifier: Programming Language :: Python :: 3.10
Classifier: Programming Language :: Python :: 3.11
Classifier: Programming Language :: Python :: 3.12
Classifier: Programming Language :: Python :: 3.13
Requires-Python: >=3.9
Requires-Dist: ase
Requires-Dist: h5glance
Requires-Dist: h5py
Requires-Dist: loguru
Requires-Dist: numpy<2
Requires-Dist: polars>=0.18
Requires-Dist: prompt-toolkit
Requires-Dist: pymatgen
Requires-Dist: statsmodels
Requires-Dist: tables
Provides-Extra: dev
Requires-Dist: better-exceptions; extra == 'dev'
Requires-Dist: pre-commit; extra == 'dev'
Requires-Dist: pytest; extra == 'dev'
Requires-Dist: pytest-cov; extra == 'dev'
Requires-Dist: pytest-html; extra == 'dev'
Requires-Dist: pytest-instafail; extra == 'dev'
Requires-Dist: ruff; extra == 'dev'
Requires-Dist: syrupy; extra == 'dev'
Requires-Dist: twine; extra == 'dev'
Provides-Extra: manual
Requires-Dist: jieba; extra == 'manual'
Requires-Dist: sphinx; extra == 'manual'
Requires-Dist: sphinx-autodoc-typehints; extra == 'manual'
Requires-Dist: sphinx-copybutton; extra == 'manual'
Requires-Dist: sphinx-design; extra == 'manual'
Requires-Dist: sphinx-mathjax-offline; extra == 'manual'
Requires-Dist: sphinx-multiversion; extra == 'manual'
Requires-Dist: sphinx-rtd-theme; extra == 'manual'
Requires-Dist: sphinxcontrib-bibtex; extra == 'manual'
Requires-Dist: sphinxcontrib-napoleon; extra == 'manual'
Requires-Dist: sphinxcontrib-svg2pdfconverter; extra == 'manual'
